beatbox
xmltramp2
