Metadata-Version: 1.1
Name: beatbox3
Version: 0.96.1
Summary: Makes the salesforce.com SOAP API easily accessible. for Python 3
Home-page: http://www.pocketsoap.com/beatbox/
Author: Simon Fell, ported to python3 by Bill Blanchard
Author-email: UNKNOWN
License: UNKNOWN
Platform: UNKNOWN
Classifier: License :: OSI Approved :: GNU General Public License (GPL)
Classifier: Intended Audience :: Developers
